sort_alphabet/__init__.py
sort_alphabet/sorter.py
tests/__init__.py
tests/sorting.py
sort_alphabet-0.1.dist-info/LICENSE
sort_alphabet-0.1.dist-info/METADATA
sort_alphabet-0.1.dist-info/WHEEL
sort_alphabet-0.1.dist-info/top_level.txt
sort_alphabet-0.1.dist-info/RECORD
